timon_pyo3-1.1.1.dist-info/METADATA
timon_pyo3-1.1.1.dist-info/WHEEL
timon_pyo3/__init__.py
timon_pyo3/timon_pyo3.cpython-38-x86_64-linux-gnu.so
timon_pyo3-1.1.1.dist-info/RECORD
