Metadata-Version: 2.4
Name: timon_pyo3
Version: 1.1.1
Classifier: Programming Language :: Rust
Classifier: Programming Language :: Python :: Implementation :: CPython
Classifier: Programming Language :: Python :: Implementation :: PyPy
Summary: Efficient local storage and Amazon S3-compatible data synchronization for time-series data,leveraging Parquet for storage and DataFusion for querying, all wrapped in a simple and intuitive API
Author-email: Ahmed Boutaraa <ahmed@mongrov.com>
License: MIT
Requires-Python: >=3.8
